README.txt
setup.cfg
setup.py
docs/HISTORY.txt
docs/INSTALL.txt
docs/LICENSE.GPL
docs/LICENSE.txt
redturtle/__init__.py
redturtle.speedupui.pathbar.egg-info/PKG-INFO
redturtle.speedupui.pathbar.egg-info/SOURCES.txt
redturtle.speedupui.pathbar.egg-info/dependency_links.txt
redturtle.speedupui.pathbar.egg-info/entry_points.txt
redturtle.speedupui.pathbar.egg-info/namespace_packages.txt
redturtle.speedupui.pathbar.egg-info/not-zip-safe
redturtle.speedupui.pathbar.egg-info/paster_plugins.txt
redturtle.speedupui.pathbar.egg-info/requires.txt
redturtle.speedupui.pathbar.egg-info/top_level.txt
redturtle/speedupui/__init__.py
redturtle/speedupui/pathbar/__init__.py
redturtle/speedupui/pathbar/configure.zcml
redturtle/speedupui/pathbar/overrides.zcml
redturtle/speedupui/pathbar/path_bar.pt
redturtle/speedupui/pathbar/path_bar.py
redturtle/speedupui/pathbar/browser/__init__.py
redturtle/speedupui/pathbar/browser/configure.zcml
redturtle/speedupui/pathbar/browser/navigation.py
redturtle/speedupui/pathbar/browser/speedupui.pathbar.css
redturtle/speedupui/pathbar/profiles/default/cssregistry.xml
redturtle/speedupui/pathbar/profiles/default/metadata.xml