Metadata-Version: 1.0
Name: redturtle.speedupui.pathbar
Version: 0.1.0dev
Summary: A Plone pathbar (breadcrumbs) viewlet implementation with more interactive features
Home-page: http://svn.plone.org/svn/collective/redturtle.speedupui.pathbar
Author: Luca Fabbri (keul)
Author-email: luca.fabbri@redturtle.net
License: GPL
Keywords: plone pathbar breadcrumbs speedupui redturtle
Platform: UNKNOWN
Classifier: Development Status :: 3 - Alpha
Classifier: Framework :: Plone
Classifier: Programming Language :: Python
Classifier: Topic :: Software Development :: Libraries :: Python Modules
